keba_kecontact/__init__.py
keba_kecontact/__main__.py
keba_kecontact/charging_station.py
keba_kecontact/charging_station_info.py
keba_kecontact/connection.py
keba_kecontact/const.py
keba_kecontact/emulator.py
keba_kecontact/utils.py
keba_kecontact-4.3.0.dist-info/METADATA
keba_kecontact-4.3.0.dist-info/WHEEL
keba_kecontact-4.3.0.dist-info/licenses/LICENSE
keba_kecontact-4.3.0.dist-info/RECORD
