Metadata-Version: 2.4
Name: keba_kecontact
Version: 4.3.0
Summary: A python library to communicate with the KEBA charging stations via udp
Author-email: Philipp Danner <philipp@danner-web.de>
License-File: LICENSE
Classifier: Development Status :: 5 - Production/Stable
Classifier: Intended Audience :: Developers
Classifier: License :: OSI Approved :: MIT License
Requires-Python: >=3.11
Requires-Dist: asyncio-dgram>=2.2.0
Requires-Dist: ifaddr>=0.2.0
Provides-Extra: dev
Requires-Dist: pytest; extra == 'dev'
